flask_auxs/__init__.py
flask_auxs/base.py
flask_auxs/errors.py
flask_auxs/exceptions.py
flask_auxs/url_helpers.py
flask_auxs-0.1.0.dist-info/LICENSE
flask_auxs-0.1.0.dist-info/METADATA
flask_auxs-0.1.0.dist-info/WHEEL
flask_auxs-0.1.0.dist-info/RECORD
