Metadata-Version: 2.1
Name: Flask-Auxs
Version: 0.1.0
Summary: Flask extension for providing auxiliary components to be used by different projects
Author: Rafal Padkowski
Author-email: rafaelp@poczta.onet.pl
Requires-Python: >=3.10
Classifier: Programming Language :: Python :: 3
Classifier: Programming Language :: Python :: 3.10
Classifier: Programming Language :: Python :: 3.11
Classifier: Programming Language :: Python :: 3.12
Requires-Dist: flask (>=3.0.0)
